{
  "kind": "os::Exec",
  "id": "build",
  "fqn": "example-website-app/markmiller/example-website/build",
  "seq": 0,
  "data": {},
  "status": "created",
  "output": {
    "id": "build",
    "command": "npm run build",
    "inheritStdio": true,
    "exitCode": 0,
    "stdout": "",
    "stderr": "",
    "executedAt": 1746672882291,
    "completed": true,
    "Kind": "os::Exec",
    "ID": "build",
    "FQN": "example-website-app/markmiller/example-website/build",
    "Seq": 0
  },
  "props": {
    "command": "npm run build"
  }
}